decev/__init__.py
decev/decev.py
decev-1.2.0.dist-info/LICENSE
decev-1.2.0.dist-info/METADATA
decev-1.2.0.dist-info/WHEEL
decev-1.2.0.dist-info/top_level.txt
decev-1.2.0.dist-info/RECORD
