Metadata-Version: 2.1
Name: decev
Version: 1.2.0
Summary: Event handlers with decorators
Home-page: https://github.com/dantechguy/decev
Author: Dan W-B
Author-email: d@nielwb.com
License: UNKNOWN
Platform: UNKNOWN
Classifier: Programming Language :: Python :: 3
Classifier: License :: OSI Approved :: MIT License
Classifier: Operating System :: OS Independent
Requires-Python: >=3.6
